{
  "operations": {
    "/users/{user-id}/contactFolders": {
      "apiVersion": "v1.0-beta",
      "originalLocation": "/openApiDocs/beta/PersonalContacts.yml"
    },
    "/users/{user-id}/contactFolders/{contactFolder-id}": {
      "apiVersion": "v1.0-beta",
      "originalLocation": "/openApiDocs/beta/PersonalContacts.yml"
    },
    "/users/{user-id}/contactFolders/{contactFolder-id}/childFolders": {
      "apiVersion": "v1.0-beta",
      "originalLocation": "/openApiDocs/beta/PersonalContacts.yml"
    },
    "/users/{user-id}/contactFolders/{contactFolder-id}/childFolders/{contactFolder-id1}": {
      "apiVersion": "v1.0-beta",
      "originalLocation": "/openApiDocs/beta/PersonalContacts.yml"
    },
    "/users/{user-id}/contactFolders/{contactFolder-id}/contacts": {
      "apiVersion": "v1.0-beta",
      "originalLocation": "/openApiDocs/beta/PersonalContacts.yml"
    },
    "/users/{user-id}/contactFolders/{contactFolder-id}/contacts/{contact-id}": {
      "apiVersion": "v1.0-beta",
      "originalLocation": "/openApiDocs/beta/PersonalContacts.yml"
    },
    "/users/{user-id}/contactFolders/{contactFolder-id}/contacts/{contact-id}/extensions": {
      "apiVersion": "v1.0-beta",
      "originalLocation": "/openApiDocs/beta/PersonalContacts.yml"
    },
    "/users/{user-id}/contactFolders/{contactFolder-id}/contacts/{contact-id}/extensions/{extension-id}": {
      "apiVersion": "v1.0-beta",
      "originalLocation": "/openApiDocs/beta/PersonalContacts.yml"
    },
    "/users/{user-id}/contactFolders/{contactFolder-id}/contacts/{contact-id}/multiValueExtendedProperties": {
      "apiVersion": "v1.0-beta",
      "originalLocation": "/openApiDocs/beta/PersonalContacts.yml"
    },
    "/users/{user-id}/contactFolders/{contactFolder-id}/contacts/{contact-id}/multiValueExtendedProperties/{multiValueLegacyExtendedProperty-id}": {
      "apiVersion": "v1.0-beta",
      "originalLocation": "/openApiDocs/beta/PersonalContacts.yml"
    },
    "/users/{user-id}/contactFolders/{contactFolder-id}/contacts/{contact-id}/photo": {
      "apiVersion": "v1.0-beta",
      "originalLocation": "/openApiDocs/beta/PersonalContacts.yml"
    },
    "/users/{user-id}/contactFolders/{contactFolder-id}/contacts/{contact-id}/photo/$value": {
      "apiVersion": "v1.0-beta",
      "originalLocation": "/openApiDocs/beta/PersonalContacts.yml"
    },
    "/users/{user-id}/contactFolders/{contactFolder-id}/contacts/{contact-id}/singleValueExtendedProperties": {
      "apiVersion": "v1.0-beta",
      "originalLocation": "/openApiDocs/beta/PersonalContacts.yml"
    },
    "/users/{user-id}/contactFolders/{contactFolder-id}/contacts/{contact-id}/singleValueExtendedProperties/{singleValueLegacyExtendedProperty-id}": {
      "apiVersion": "v1.0-beta",
      "originalLocation": "/openApiDocs/beta/PersonalContacts.yml"
    },
    "/users/{user-id}/contactFolders/{contactFolder-id}/multiValueExtendedProperties": {
      "apiVersion": "v1.0-beta",
      "originalLocation": "/openApiDocs/beta/PersonalContacts.yml"
    },
    "/users/{user-id}/contactFolders/{contactFolder-id}/multiValueExtendedProperties/{multiValueLegacyExtendedProperty-id}": {
      "apiVersion": "v1.0-beta",
      "originalLocation": "/openApiDocs/beta/PersonalContacts.yml"
    },
    "/users/{user-id}/contactFolders/{contactFolder-id}/singleValueExtendedProperties": {
      "apiVersion": "v1.0-beta",
      "originalLocation": "/openApiDocs/beta/PersonalContacts.yml"
    },
    "/users/{user-id}/contactFolders/{contactFolder-id}/singleValueExtendedProperties/{singleValueLegacyExtendedProperty-id}": {
      "apiVersion": "v1.0-beta",
      "originalLocation": "/openApiDocs/beta/PersonalContacts.yml"
    },
    "/users/{user-id}/contacts": {
      "apiVersion": "v1.0-beta",
      "originalLocation": "/openApiDocs/beta/PersonalContacts.yml"
    },
    "/users/{user-id}/contacts/{contact-id}": {
      "apiVersion": "v1.0-beta",
      "originalLocation": "/openApiDocs/beta/PersonalContacts.yml"
    },
    "/users/{user-id}/contacts/{contact-id}/extensions": {
      "apiVersion": "v1.0-beta",
      "originalLocation": "/openApiDocs/beta/PersonalContacts.yml"
    },
    "/users/{user-id}/contacts/{contact-id}/extensions/{extension-id}": {
      "apiVersion": "v1.0-beta",
      "originalLocation": "/openApiDocs/beta/PersonalContacts.yml"
    },
    "/users/{user-id}/contacts/{contact-id}/multiValueExtendedProperties": {
      "apiVersion": "v1.0-beta",
      "originalLocation": "/openApiDocs/beta/PersonalContacts.yml"
    },
    "/users/{user-id}/contacts/{contact-id}/multiValueExtendedProperties/{multiValueLegacyExtendedProperty-id}": {
      "apiVersion": "v1.0-beta",
      "originalLocation": "/openApiDocs/beta/PersonalContacts.yml"
    },
    "/users/{user-id}/contacts/{contact-id}/photo": {
      "apiVersion": "v1.0-beta",
      "originalLocation": "/openApiDocs/beta/PersonalContacts.yml"
    },
    "/users/{user-id}/contacts/{contact-id}/photo/$value": {
      "apiVersion": "v1.0-beta",
      "originalLocation": "/openApiDocs/beta/PersonalContacts.yml"
    },
    "/users/{user-id}/contacts/{contact-id}/singleValueExtendedProperties": {
      "apiVersion": "v1.0-beta",
      "originalLocation": "/openApiDocs/beta/PersonalContacts.yml"
    },
    "/users/{user-id}/contacts/{contact-id}/singleValueExtendedProperties/{singleValueLegacyExtendedProperty-id}": {
      "apiVersion": "v1.0-beta",
      "originalLocation": "/openApiDocs/beta/PersonalContacts.yml"
    }
  },
  "resources": []
}
