{
  "resources": [],
  "operations": {
    "/deviceManagement/conditionalAccessSettings": {
      "apiVersion": "v1.0",
      "originalLocation": "/openApiDocs/v1.0/DeviceManagement.Enrolment.yml"
    },
    "/deviceManagement/deviceEnrollmentConfigurations": {
      "apiVersion": "v1.0",
      "originalLocation": "/openApiDocs/v1.0/DeviceManagement.Enrolment.yml"
    },
    "/deviceManagement/deviceEnrollmentConfigurations/{deviceEnrollmentConfiguration-id}": {
      "apiVersion": "v1.0",
      "originalLocation": "/openApiDocs/v1.0/DeviceManagement.Enrolment.yml"
    },
    "/deviceManagement/deviceEnrollmentConfigurations/{deviceEnrollmentConfiguration-id}/assignments": {
      "apiVersion": "v1.0",
      "originalLocation": "/openApiDocs/v1.0/DeviceManagement.Enrolment.yml"
    },
    "/deviceManagement/deviceEnrollmentConfigurations/{deviceEnrollmentConfiguration-id}/assignments/{enrollmentConfigurationAssignment-id}": {
      "apiVersion": "v1.0",
      "originalLocation": "/openApiDocs/v1.0/DeviceManagement.Enrolment.yml"
    },
    "/deviceManagement/importedWindowsAutopilotDeviceIdentities": {
      "apiVersion": "v1.0",
      "originalLocation": "/openApiDocs/v1.0/DeviceManagement.Enrolment.yml"
    },
    "/deviceManagement/importedWindowsAutopilotDeviceIdentities/{importedWindowsAutopilotDeviceIdentity-id}": {
      "apiVersion": "v1.0",
      "originalLocation": "/openApiDocs/v1.0/DeviceManagement.Enrolment.yml"
    },
    "/deviceManagement/windowsAutopilotDeviceIdentities": {
      "apiVersion": "v1.0",
      "originalLocation": "/openApiDocs/v1.0/DeviceManagement.Enrolment.yml"
    },
    "/deviceManagement/windowsAutopilotDeviceIdentities/{windowsAutopilotDeviceIdentity-id}": {
      "apiVersion": "v1.0",
      "originalLocation": "/openApiDocs/v1.0/DeviceManagement.Enrolment.yml"
    },
    "/roleManagement": {
      "apiVersion": "v1.0",
      "originalLocation": "/openApiDocs/v1.0/DeviceManagement.Enrolment.yml"
    },
    "/roleManagement/directory": {
      "apiVersion": "v1.0",
      "originalLocation": "/openApiDocs/v1.0/DeviceManagement.Enrolment.yml"
    },
    "/roleManagement/directory/roleAssignments": {
      "apiVersion": "v1.0",
      "originalLocation": "/openApiDocs/v1.0/DeviceManagement.Enrolment.yml"
    },
    "/roleManagement/directory/roleAssignments/{unifiedRoleAssignment-id}": {
      "apiVersion": "v1.0",
      "originalLocation": "/openApiDocs/v1.0/DeviceManagement.Enrolment.yml"
    },
    "/roleManagement/directory/roleAssignments/{unifiedRoleAssignment-id}/appScope": {
      "apiVersion": "v1.0",
      "originalLocation": "/openApiDocs/v1.0/DeviceManagement.Enrolment.yml"
    },
    "/roleManagement/directory/roleAssignments/{unifiedRoleAssignment-id}/directoryScope": {
      "apiVersion": "v1.0",
      "originalLocation": "/openApiDocs/v1.0/DeviceManagement.Enrolment.yml"
    },
    "/roleManagement/directory/roleAssignments/{unifiedRoleAssignment-id}/principal": {
      "apiVersion": "v1.0",
      "originalLocation": "/openApiDocs/v1.0/DeviceManagement.Enrolment.yml"
    },
    "/roleManagement/directory/roleAssignments/{unifiedRoleAssignment-id}/roleDefinition": {
      "apiVersion": "v1.0",
      "originalLocation": "/openApiDocs/v1.0/DeviceManagement.Enrolment.yml"
    },
    "/roleManagement/directory/roleDefinitions": {
      "apiVersion": "v1.0",
      "originalLocation": "/openApiDocs/v1.0/DeviceManagement.Enrolment.yml"
    },
    "/roleManagement/directory/roleDefinitions/{unifiedRoleDefinition-id}": {
      "apiVersion": "v1.0",
      "originalLocation": "/openApiDocs/v1.0/DeviceManagement.Enrolment.yml"
    },
    "/roleManagement/directory/roleDefinitions/{unifiedRoleDefinition-id}/inheritsPermissionsFrom": {
      "apiVersion": "v1.0",
      "originalLocation": "/openApiDocs/v1.0/DeviceManagement.Enrolment.yml"
    },
    "/roleManagement/directory/roleDefinitions/{unifiedRoleDefinition-id}/inheritsPermissionsFrom/{unifiedRoleDefinition-id1}": {
      "apiVersion": "v1.0",
      "originalLocation": "/openApiDocs/v1.0/DeviceManagement.Enrolment.yml"
    },
    "/roleManagement/entitlementManagement": {
      "apiVersion": "v1.0",
      "originalLocation": "/openApiDocs/v1.0/DeviceManagement.Enrolment.yml"
    },
    "/roleManagement/entitlementManagement/roleAssignments": {
      "apiVersion": "v1.0",
      "originalLocation": "/openApiDocs/v1.0/DeviceManagement.Enrolment.yml"
    },
    "/roleManagement/entitlementManagement/roleAssignments/{unifiedRoleAssignment-id}": {
      "apiVersion": "v1.0",
      "originalLocation": "/openApiDocs/v1.0/DeviceManagement.Enrolment.yml"
    },
    "/roleManagement/entitlementManagement/roleAssignments/{unifiedRoleAssignment-id}/appScope": {
      "apiVersion": "v1.0",
      "originalLocation": "/openApiDocs/v1.0/DeviceManagement.Enrolment.yml"
    },
    "/roleManagement/entitlementManagement/roleAssignments/{unifiedRoleAssignment-id}/directoryScope": {
      "apiVersion": "v1.0",
      "originalLocation": "/openApiDocs/v1.0/DeviceManagement.Enrolment.yml"
    },
    "/roleManagement/entitlementManagement/roleAssignments/{unifiedRoleAssignment-id}/principal": {
      "apiVersion": "v1.0",
      "originalLocation": "/openApiDocs/v1.0/DeviceManagement.Enrolment.yml"
    },
    "/roleManagement/entitlementManagement/roleAssignments/{unifiedRoleAssignment-id}/roleDefinition": {
      "apiVersion": "v1.0",
      "originalLocation": "/openApiDocs/v1.0/DeviceManagement.Enrolment.yml"
    },
    "/roleManagement/entitlementManagement/roleDefinitions": {
      "apiVersion": "v1.0",
      "originalLocation": "/openApiDocs/v1.0/DeviceManagement.Enrolment.yml"
    },
    "/roleManagement/entitlementManagement/roleDefinitions/{unifiedRoleDefinition-id}": {
      "apiVersion": "v1.0",
      "originalLocation": "/openApiDocs/v1.0/DeviceManagement.Enrolment.yml"
    },
    "/roleManagement/entitlementManagement/roleDefinitions/{unifiedRoleDefinition-id}/inheritsPermissionsFrom": {
      "apiVersion": "v1.0",
      "originalLocation": "/openApiDocs/v1.0/DeviceManagement.Enrolment.yml"
    },
    "/roleManagement/entitlementManagement/roleDefinitions/{unifiedRoleDefinition-id}/inheritsPermissionsFrom/{unifiedRoleDefinition-id1}": {
      "apiVersion": "v1.0",
      "originalLocation": "/openApiDocs/v1.0/DeviceManagement.Enrolment.yml"
    }
  }
}
